{
  "real-estate": [
    { "id": "1",
      "title": "Entire flat",
      "image": "https://www.aproperties.es/thumb?src=/media/properties/27899/27899_1617964436654.jpg&w=640&h=480",
      "price": "83",
      "desc": "1 bedroom"
    },
    { "id": "2",
      "title": "Entire flat",
      "image": "https://www.aproperties.es/thumb?src=/media/properties/27899/27899_1617964436654.jpg&w=640&h=480",
      "price": "93",
      "desc": "3 bedroom"
    },
    { "id": "3",
      "title": "Entire flat",
      "image": "https://www.aproperties.es/thumb?src=/media/properties/27899/27899_1617964436654.jpg&w=640&h=480",
      "price": "93",
      "desc": "3 bedroom"
    },
    { "id": "4",
      "title": "Entire flat",
      "image": "https://www.aproperties.es/thumb?src=/media/properties/27899/27899_1617964436654.jpg&w=640&h=480",
      "price": "83",
      "desc": "1 bedroom"
    },
    { "id": "5",
      "title": "Entire flat",
      "image": "https://www.aproperties.es/thumb?src=/media/properties/27899/27899_1617964436654.jpg&w=640&h=480",
      "price": "93",
      "desc": "3 bedroom"
    },
    { "id": "6",
      "title": "Entire flat",
      "image": "https://www.aproperties.es/thumb?src=/media/properties/27899/27899_1617964436654.jpg&w=640&h=480",
      "price": "93",
      "desc": "3 bedroom"
    }
  ]
}